usl/__init__.py
usl/ask_ai.py
usl/cli.py
usl/docs.py
usl/login_premium.py
usl/query.py
usl/status.py
usl/welcome.py
usl/__pycache__/__init__.cpython-38.pyc
usl/__pycache__/cli.cpython-38.pyc
usl/commands/__init__.py
usl/commands/ascii_art.py
usl/commands/config.py
usl/commands/feedback.py
usl/commands/login_freemium.py
usl/commands/query.py
usl/commands/scrape.py
usl/commands/spinner.py
usl/commands/__pycache__/__init__.cpython-38.pyc
usl/commands/__pycache__/ascii_art.cpython-38.pyc
usl/commands/__pycache__/ask_ai.cpython-38.pyc
usl/commands/__pycache__/config.cpython-38.pyc
usl/commands/__pycache__/docs.cpython-38.pyc
usl/commands/__pycache__/feedback.cpython-38.pyc
usl/commands/__pycache__/login.cpython-38.pyc
usl/commands/__pycache__/login_freemium.cpython-38.pyc
usl/commands/__pycache__/login_premium.cpython-38.pyc
usl/commands/__pycache__/query.cpython-38.pyc
usl/commands/__pycache__/scrape.cpython-38.pyc
usl/commands/__pycache__/spinner.cpython-38.pyc
usl/commands/__pycache__/status.cpython-38.pyc
usl/commands/__pycache__/welcome.cpython-38.pyc
usl/utils/__init__.py
usl/utils/db.py
usl/utils/__pycache__/__init__.cpython-38.pyc
usl/utils/__pycache__/db.cpython-38.pyc
spider_cli-0.2.4.dist-info/METADATA
spider_cli-0.2.4.dist-info/WHEEL
spider_cli-0.2.4.dist-info/entry_points.txt
spider_cli-0.2.4.dist-info/top_level.txt
spider_cli-0.2.4.dist-info/RECORD
