Metadata-Version: 2.1
Name: spider-cli
Version: 0.2.4
Summary: SPIDER: Secure Proxy Infrastructure for Data Extraction and Retrieval
Home-page: https://github.com/minakilabs-official/spider-cli
Author: Andrew Polykandriotis
Author-email: support@minakilabs.com
License: UNKNOWN
Platform: UNKNOWN
Classifier: Programming Language :: Python :: 3
Classifier: Operating System :: OS Independent
Requires-Python: >=3.6
Requires-Dist: art
Requires-Dist: click
Requires-Dist: halo
Requires-Dist: jmespath
Requires-Dist: python-dotenv
Requires-Dist: requests
